{
  "id": "set_20260102_154519_819",
  "name": "테스트",
  "created_at": "2026-01-02T15:45:19.414334",
  "level_count": 10,
  "difficulty_profile": [
    0.11,
    0.16,
    0.11,
    0.22,
    0.32,
    0.3,
    0.45,
    0.38,
    0.53,
    0.67
  ],
  "actual_difficulties": [
    0.16933333333333334,
    0.20808333333333334,
    0.16383333333333333,
    0.23183333333333334,
    0.27141666666666664,
    0.25991666666666663,
    0.4035,
    0.3476666666666667,
    0.4453333333333333,
    0.5491666666666667
  ],
  "grades": [
    "S",
    "A",
    "S",
    "A",
    "A",
    "A",
    "B",
    "A",
    "B",
    "B"
  ],
  "generation_config": {
    "grid_size": [
      7,
      7
    ],
    "max_layers": 5,
    "tile_types": [
      "t0",
      "t2",
      "t4",
      "t5",
      "t6"
    ],
    "obstacle_types": [
      "chain",
      "frog"
    ],
    "goals": [
      {
        "type": "craft",
        "direction": "s",
        "count": 3
      },
      {
        "type": "craft",
        "direction": "n",
        "count": 3
      },
      {
        "type": "craft",
        "direction": "e",
        "count": 3
      },
      {
        "type": "craft",
        "direction": "w",
        "count": 3
      }
    ]
  }
}