{
  "layer": 4,
  "useTileCount": 5,
  "randSeed": 938919,
  "layer_0": {
    "col": "8",
    "row": "8",
    "tiles": {
      "3_5": [
        "t4",
        ""
      ],
      "5_5": [
        "t0",
        ""
      ],
      "3_2": [
        "t4",
        ""
      ],
      "4_3": [
        "t2",
        ""
      ],
      "2_4": [
        "t2",
        ""
      ],
      "5_4": [
        "t0",
        ""
      ],
      "3_3": [
        "t6",
        ""
      ],
      "4_4": [
        "t4",
        ""
      ],
      "4_5": [
        "t4",
        ""
      ],
      "2_5": [
        "t2",
        ""
      ],
      "3_6": [
        "t2",
        ""
      ],
      "5_2": [
        "t6",
        ""
      ],
      "2_3": [
        "t0",
        ""
      ],
      "3_4": [
        "t4",
        ""
      ],
      "3_1": [
        "t0",
        ""
      ],
      "4_2": [
        "t0",
        ""
      ],
      "5_3": [
        "t0",
        ""
      ],
      "2_2": [
        "t5",
        ""
      ]
    },
    "num": "18"
  },
  "layer_1": {
    "col": "7",
    "row": "7",
    "tiles": {
      "3_5": [
        "t6",
        ""
      ],
      "3_2": [
        "t4",
        ""
      ],
      "4_3": [
        "t4",
        ""
      ],
      "3_3": [
        "t0",
        ""
      ],
      "4_4": [
        "t2",
        ""
      ],
      "1_3": [
        "t2",
        ""
      ],
      "4_2": [
        "t4",
        ""
      ],
      "2_3": [
        "t4",
        ""
      ],
      "3_4": [
        "t6",
        ""
      ],
      "3_1": [
        "t0",
        ""
      ],
      "2_4": [
        "t6",
        ""
      ],
      "5_3": [
        "t6",
        ""
      ],
      "2_2": [
        "t5",
        ""
      ]
    },
    "num": "13"
  },
  "layer_2": {
    "col": "8",
    "row": "8",
    "tiles": {
      "3_5": [
        "t2",
        ""
      ],
      "5_5": [
        "t2",
        ""
      ],
      "3_2": [
        "t6",
        ""
      ],
      "2_4": [
        "t5",
        ""
      ],
      "5_4": [
        "t4",
        "ice"
      ],
      "2_5": [
        "t4",
        ""
      ],
      "4_5": [
        "t2",
        ""
      ],
      "0_3": [
        "t5",
        ""
      ],
      "5_2": [
        "t4",
        ""
      ],
      "2_3": [
        "t5",
        ""
      ],
      "4_2": [
        "t2",
        ""
      ],
      "5_3": [
        "t2",
        ""
      ],
      "0_4": [
        "t6",
        ""
      ],
      "2_2": [
        "t2",
        ""
      ]
    },
    "num": "14"
  },
  "layer_3": {
    "col": "7",
    "row": "7",
    "tiles": {
      "3_5": [
        "t6",
        ""
      ],
      "3_2": [
        "t5",
        ""
      ],
      "4_3": [
        "t2",
        ""
      ],
      "3_3": [
        "t0",
        ""
      ],
      "4_4": [
        "t5",
        ""
      ],
      "1_3": [
        "t5",
        ""
      ],
      "4_2": [
        "t2",
        ""
      ],
      "2_3": [
        "t6",
        ""
      ],
      "3_4": [
        "t6",
        ""
      ],
      "3_1": [
        "t2",
        ""
      ],
      "2_4": [
        "t6",
        ""
      ],
      "2_2": [
        "t5",
        ""
      ],
      "0_5": [
        "craft_s",
        "",
        [
          3
        ]
      ]
    },
    "num": "13"
  },
  "layer_4": {
    "col": "8",
    "row": "8",
    "tiles": {},
    "num": "0"
  },
  "layer_5": {
    "col": "7",
    "row": "7",
    "tiles": {},
    "num": "0"
  },
  "layer_6": {
    "col": "8",
    "row": "8",
    "tiles": {},
    "num": "0"
  },
  "goalCount": {
    "craft_s": 3
  },
  "max_moves": 60,
  "target_difficulty": 0.44999999999999996,
  "symmetry_mode": "vertical",
  "pattern_type": "aesthetic",
  "level_index": 46,
  "name": "Symmetry Test 3 - Level 46",
  "id": "set_1767864870539_746o4ek13_level_046"
}